{"results_found": 607, "results_start": 0, "results_shown": 20, "restaurants": [{"restaurant": {"R": {"res_id": 18673403}, "apikey": "745c5f1b6907194a76b81269f31e9046", "id": "18673403", "name": "Rodeo Cantina & Kitchen", "url": "https://www.zomato.com/ncr/rodeo-cantina-kitchen-connaught-place-new-delhi?utm_source=api_basic_user&utm_medium=api&utm_campaign=v2.1", "location": {"address": "A-12, Inner Circle, Connaught Place, New Delhi", "locality": "Connaught Place", "city": "New Delhi", "city_id": 1, "latitude": "28.6331602547", "longitude": "77.2179423273", "zipcode": "110001", "country_id": 1, "locality_verbose": "Connaught Place, New Delhi"}, "switch_to_order_menu": 0, "cuisines": "Mexican", "average_cost_for_two": 1800, "price_range": 3, "currency": "Rs.", "offers": [], "zomato_events": [{"event": {"event_id": 223339, "friendly_start_date": "03 June, 2018", "friendly_end_date": "31 March", "friendly_timing_str": "Sunday, 3rd June - Sunday, 31st March", "start_date": "2018-06-03", "end_date": "2019-03-31", "end_time": "16:00:00", "start_time": "12:30:00", "is_active": 1, "date_added": "2018-06-01 15:54:36", "photos": [{"photo": {"url": "https://b.zmtcdn.com/data/zomato_events/photos/068/a741bd2047306360897f842ad96c6068_1537507082.jpg", "thumb_url": "https://b.zmtcdn.com/data/zomato_events/photos/068/a741bd2047306360897f842ad96c6068_1537507082.jpg?fit=around%7C100%3A100&crop=100%3A100%3B%2A%2C%2A", "order": 0, "md5sum": "a741bd2047306360897f842ad96c6068", "id": 351045, "photo_id": 351045, "uuid": 1537507044665236, "type": "NORMAL"}}], "restaurants": [], "is_valid": 1, "share_url": "http://www.zoma.to/r/0", "show_share_url": 0, "title": "Sunday Bruncharita", "description": "Every Sunday! Unlimited Margaritas, Sangria, Domestic Beer, with unlimited Nachos & Salsa Roja, with a choice of Quesadillas, Burritos, Tacos, Enchiladas, and Churros\nPrice:\u00a0Rs 1650 plus taxes\nTerms and Conditons : Valid for 2 hours from first order, Amigos & Amigas must order one drink at a time!", "display_time": "12:30 pm - 04:00 pm", "display_date": "03 June - 31 March", "is_end_time_set": 1, "disclaimer": "Restaurants are solely responsible for the service; availability and quality of the events including all or any cancellations/ modifications/ complaints.", "event_category": 0, "event_category_name": "", "book_link": "", "types": [{"name": "All you can Eat", "color": "#F96C6A"}], "share_data": {"should_show": 0}}}, {"event": {"event_id": 256469, "friendly_start_date": "21 September, 2018", "friendly_end_date": "31 March", "friendly_timing_str": "Friday, 21st September - Sunday, 31st March", "start_date": "2018-09-21", "end_date": "2019-03-31", "end_time": "00:30:00", "start_time": "16:00:00", "is_active": 1, "date_added": "2018-09-21 10:52:40", "photos": [{"photo": {"url": "https://b.zmtcdn.com/data/zomato_events/photos/f9f/08206e5588dd932fd1558e0870334f9f_1537507360.jpg", "thumb_url": "https://b.zmtcdn.com/data/zomato_events/photos/f9f/08206e5588dd932fd1558e0870334f9f_1537507360.jpg?fit=around%7C100%3A100&crop=100%3A100%3B%2A%2C%2A", "order": 0, "md5sum": "08206e5588dd932fd1558e0870334f9f", "id": 351048, "photo_id": 351048, "uuid": 1537507322729115, "type": "NORMAL"}}, {"photo": {"url": "https://b.zmtcdn.com/data/zomato_events/photos/752/bc4cffa1d1d01399bbeaefb1f9238752_1537507361.jpg", "thumb_url": "https://b.zmtcdn.com/data/zomato_events/photos/752/bc4cffa1d1d01399bbeaefb1f9238752_1537507361.jpg?fit=around%7C100%3A100&crop=100%3A100%3B%2A%2C%2A", "order": 1, "md5sum": "bc4cffa1d1d01399bbeaefb1f9238752", "id": 351049, "photo_id": 351049, "uuid": 1537507329088440, "type": "NORMAL"}}], "restaurants": [], "is_valid": 1, "share_url": "http://www.zoma.to/r/0", "show_share_url": 0, "title": "Loco Loco", "description": "LOCO LOCO is better than HAPPY HOURS! \nMonday - Thursday from 4:00pm - 7:30pm and from 11:00pm - 12:30am were serving drinks starting from Rs 99! *\n\nDrink responsibly!", "display_time": "04:00 pm - 12:30 am", "display_date": "21 September - 31 March", "is_end_time_set": 1, "disclaimer": "Restaurants are solely responsible for the service; availability and quality of the events including all or any cancellations/ modifications/ complaints.", "event_category": 0, "event_category_name": "", "book_link": "", "types": [{"name": "Happy Hours", "color": "#E23744"}], "share_data": {"should_show": 0}}}, {"event": {"event_id": 221638, "friendly_start_date": "04 October, 2018", "friendly_end_date": "15 March", "friendly_timing_str": "Thursday, 4th October - Friday, 15th March", "start_date": "2018-10-04", "end_date": "2019-03-15", "end_time": "23:00:00", "start_time": "19:30:00", "is_active": 1, "date_added": "2018-05-26 13:32:11", "photos": [{"photo": {"url": "https://b.zmtcdn.com/data/zomato_events/photos/6ec/36568c270d2f9cf5311c17c8bc7a26ec_1527321731.jpg", "thumb_url": "https://b.zmtcdn.com/data/zomato_events/photos/6ec/36568c270d2f9cf5311c17c8bc7a26ec_1527321731.jpg?fit=around%7C100%3A100&crop=100%3A100%3B%2A%2C%2A", "order": 0, "md5sum": "36568c270d2f9cf5311c17c8bc7a26ec", "id": 309830, "photo_id": 309830, "uuid": 1527321611067453, "type": "NORMAL"}}], "restaurants": [], "is_valid": 1, "share_url": "http://www.zoma.to/r/0", "show_share_url": 0, "title": "Senoritas night!", "description": "Were excited for our Senoritas aka Ladies Night every Wednesday from 7:30pm- 11:00pm! \n\n1+1 on all Margaritas & Micheladas for all ladies \n\nGroups of 6 girls or more get a free round of tequila infused shots on us!", "display_time": "07:30 pm - 11:00 pm", "display_date": "04 October - 15 March", "is_end_time_set": 1, "disclaimer": "Restaurants are solely responsible for the service; availability and quality of the events including all or any cancellations/ modifications/ complaints.", "event_category": 0, "event_category_name": "", "book_link": "", "types": [{"name": "Ladies Night", "color": "#0AAC9B"}], "share_data": {"should_show": 0}}}], "opentable_support": 0, "is_zomato_book_res": 0, "mezzo_provider": "OTHER", "is_book_form_web_view": 0, "book_form_web_view_url": "", "book_again_url": "", "thumb": "https://b.zmtcdn.com/data/pictures/3/18673403/d195204704e85977e64252f0916ed38a.jpg?fit=around%7C200%3A200&crop=200%3A200%3B%2A%2C%2A", "user_rating": {"aggregate_rating": "4.1", "rating_text": "Very Good", "rating_color": "5BA829", "votes": "515"}, "photos_url": "https://www.zomato.com/ncr/rodeo-cantina-kitchen-connaught-place-new-delhi/photos?utm_source=api_basic_user&utm_medium=api&utm_campaign=v2.1#tabtop", "menu_url": "https://www.zomato.com/ncr/rodeo-cantina-kitchen-connaught-place-new-delhi/menu?utm_source=api_basic_user&utm_medium=api&utm_campaign=v2.1&openSwipeBox=menu&showMinimal=1#tabtop", "featured_image": "https://b.zmtcdn.com/data/pictures/3/18673403/d195204704e85977e64252f0916ed38a.jpg?output-format=webp", "medio_provider": 1, "has_online_delivery": 0, "is_delivering_now": 0, "include_bogo_offers": true, "deeplink": "zomato://restaurant/18673403", "is_table_reservation_supported": 1, "has_table_booking": 0, "events_url": "https://www.zomato.com/ncr/rodeo-cantina-kitchen-connaught-place-new-delhi/events#tabtop?utm_source=api_basic_user&utm_medium=api&utm_campaign=v2.1", "establishment_types": []}}, {"restaurant": {"R": {"res_id": 18624770}, "apikey": "745c5f1b6907194a76b81269f31e9046", "id": "18624770", "name": "The Rolling Kitchen", "url": "https://www.zomato.com/ncr/the-rolling-kitchen-dlf-phase-4-gurgaon?utm_source=api_basic_user&utm_medium=api&utm_campaign=v2.1", "location": {"address": "DLF Phase 4, Gurgaon", "locality": "DLF Phase 4", "city": "Gurgaon", "city_id": 1, "latitude": "28.4682925218", "longitude": "77.0831868052", "zipcode": "", "country_id": 1, "locality_verbose": "DLF Phase 4, Gurgaon"}, "switch_to_order_menu": 0, "cuisines": "Lebanese, Mexican", "average_cost_for_two": 600, "price_range": 2, "currency": "Rs.", "offers": [], "opentable_support": 0, "is_zomato_book_res": 0, "mezzo_provider": "OTHER", "is_book_form_web_view": 0, "book_form_web_view_url": "", "book_again_url": "", "thumb": "", "user_rating": {"aggregate_rating": "3.7", "rating_text": "Good", "rating_color": "9ACD32", "votes": "17"}, "photos_url": "https://www.zomato.com/ncr/the-rolling-kitchen-dlf-phase-4-gurgaon/photos?utm_source=api_basic_user&utm_medium=api&utm_campaign=v2.1#tabtop", "menu_url": "https://www.zomato.com/ncr/the-rolling-kitchen-dlf-phase-4-gurgaon/menu?utm_source=api_basic_user&utm_medium=api&utm_campaign=v2.1&openSwipeBox=menu&showMinimal=1#tabtop", "featured_image": "", "has_online_delivery": 1, "is_delivering_now": 0, "include_bogo_offers": true, "deeplink": "zomato://restaurant/18624770", "is_table_reservation_supported": 0, "has_table_booking": 0, "events_url": "https://www.zomato.com/ncr/the-rolling-kitchen-dlf-phase-4-gurgaon/events#tabtop?utm_source=api_basic_user&utm_medium=api&utm_campaign=v2.1", "establishment_types": []}}, {"restaurant": {"R": {"res_id": 18241537}, "apikey": "745c5f1b6907194a76b81269f31e9046", "id": "18241537", "name": "38 Barracks", "url": "https://www.zomato.com/ncr/38-barracks-connaught-place-new-delhi?utm_source=api_basic_user&utm_medium=api&utm_campaign=v2.1", "location": {"address": "M-38, Outer Circle, Opposite Shankar Market, Connaught Place, New Delhi", "locality": "Connaught Place", "city": "New Delhi", "city_id": 1, "latitude": "28.6329039419", "longitude": "77.2228252888", "zipcode": "110001", "country_id": 1, "locality_verbose": "Connaught Place, New Delhi"}, "switch_to_order_menu": 0, "cuisines": "North Indian, Italian, Chinese, Continental", "average_cost_for_two": 1600, "price_range": 3, "currency": "Rs.", "offers": [], "zomato_events": [{"event": {"event_id": 259288, "friendly_start_date": "02 January", "friendly_end_date": "31 January", "friendly_timing_str": "Wednesday, 2nd January - Thursday, 31st January", "start_date": "2019-01-02", "end_date": "2019-01-31", "end_time": "23:30:00", "start_time": "13:00:00", "is_active": 1, "date_added": "2018-09-30 13:59:29", "photos": [{"photo": {"url": "https://b.zmtcdn.com/data/zomato_events/photos/e05/4b570f3b0a607c35b21cacfa9dd01e05_1538296169.jpeg", "thumb_url": "https://b.zmtcdn.com/data/zomato_events/photos/e05/4b570f3b0a607c35b21cacfa9dd01e05_1538296169.jpeg?fit=around%7C100%3A100&crop=100%3A100%3B%2A%2C%2A", "order": 0, "md5sum": "4b570f3b0a607c35b21cacfa9dd01e05", "id": 354358, "photo_id": 354358, "uuid": 1538296151585229, "type": "NORMAL"}}], "restaurants": [], "is_valid": 1, "share_url": "http://www.zoma.to/r/0", "show_share_url": 0, "title": "Every Day Live Music ", "description": "Every Day Live Music  (Sufi song, bollywood numbers, retro, punjabi song play \nLunch & Dinner \nContact us for booking- 9717304083\n                                      9717304098", "display_time": "01:00 pm - 11:30 pm", "display_date": "02 January - 31 January", "is_end_time_set": 1, "disclaimer": "Restaurants are solely responsible for the service; availability and quality of the events including all or any cancellations/ modifications/ complaints.", "event_category": 1, "event_category_name": "", "book_link": "", "types": [], "share_data": {"should_show": 0}}}, {"event": {"event_id": 294230, "friendly_start_date": "14 January", "friendly_end_date": "16 January", "friendly_timing_str": "Monday, 14th January - Wednesday, 16th January", "start_date": "2019-01-14", "end_date": "2019-01-16", "end_time": "23:15:00", "start_time": "19:30:00", "is_active": 1, "date_added": "2019-01-02 12:56:17", "photos": [{"photo": {"url": "https://b.zmtcdn.com/data/zomato_events/photos/f09/c2f7ee8d7a2ab9e19b9b86938983bf09_1534917842.jpeg", "thumb_url": "https://b.zmtcdn.com/data/zomato_events/photos/f09/c2f7ee8d7a2ab9e19b9b86938983bf09_1534917842.jpeg?fit=around%7C100%3A100&crop=100%3A100%3B%2A%2C%2A", "order": 0, "md5sum": "c2f7ee8d7a2ab9e19b9b86938983bf09", "id": 397630, "photo_id": 397630, "uuid": 13959471557, "type": "NORMAL"}}], "restaurants": [], "is_valid": 1, "share_url": "http://www.zoma.to/r/0", "show_share_url": 0, "title": "Shivam Luthra  performing  live ", "description": "Bollywood  night\r\nlet your monday Tuesday Wednesday be a rocking one as shivam luthra is performing live here 7:30 pm onwards\r\nfor booking contact- 9717304097/98", "display_time": "07:30 pm - 11:15 pm", "display_date": "14 January - 16 January", "is_end_time_set": 1, "disclaimer": "Restaurants are solely responsible for the service; availability and quality of the events including all or any cancellations/ modifications/ complaints.", "event_category": 1, "event_category_name": "", "book_link": "", "types": [{"name": "Solo Performance", "color": "#6454B8"}], "share_data": {"should_show": 0}}}, {"event": {"event_id": 250257, "friendly_start_date": "17 January", "friendly_end_date": "17 January", "friendly_timing_str": "Thursday, 17th January", "start_date": "2019-01-17", "end_date": "2019-01-17", "end_time": "23:15:00", "start_time": "19:30:00", "is_active": 1, "date_added": "2018-08-31 19:59:41", "photos": [{"photo": {"url": "https://b.zmtcdn.com/data/zomato_events/photos/f84/7e0e4912c7968c31a7ae79473f502f84_1535969224.jpeg", "thumb_url": "https://b.zmtcdn.com/data/zomato_events/photos/f84/7e0e4912c7968c31a7ae79473f502f84_1535969224.jpeg?fit=around%7C100%3A100&crop=100%3A100%3B%2A%2C%2A", "order": 0, "md5sum": "7e0e4912c7968c31a7ae79473f502f84", "id": 344670, "photo_id": 344670, "uuid": 1535969224109549, "type": "NORMAL"}}], "restaurants": [], "is_valid": 1, "share_url": "http://www.zoma.to/r/0", "show_share_url": 0, "title": "Puneet Poddar Performing Live ", "description": "Weekdays on a high note with the frequency  Puneet  poddar live here 7.30 pm onwards\t\t\t\t\r\nFor booking contact -9717304098/83", "display_time": "07:30 pm - 11:15 pm", "display_date": "17 January", "is_end_time_set": 1, "disclaimer": "Restaurants are solely responsible for the service; availability and quality of the events including all or any cancellations/ modifications/ complaints.", "event_category": 1, "event_category_name": "", "book_link": "", "types": [{"name": "Solo Performance", "color": "#6454B8"}], "share_data": {"should_show": 0}}}, {"event": {"event_id": 285093, "friendly_start_date": "18 January", "friendly_end_date": "18 January", "friendly_timing_str": "Friday, 18th January", "start_date": "2019-01-18", "end_date": "2019-01-18", "end_time": "23:15:00", "start_time": "19:30:00", "is_active": 1, "date_added": "2018-12-14 09:05:41", "photos": [{"photo": {"url": "https://b.zmtcdn.com/data/zomato_events/photos/770/a9684c25a9f5c7b96dbffe52e2748770_1544758541.jpg", "thumb_url": "https://b.zmtcdn.com/data/zomato_events/photos/770/a9684c25a9f5c7b96dbffe52e2748770_1544758541.jpg?fit=around%7C100%3A100&crop=100%3A100%3B%2A%2C%2A", "order": 0, "md5sum": "a9684c25a9f5c7b96dbffe52e2748770", "id": 385769, "photo_id": 385769, "uuid": 58538058455, "type": "FEATURED"}}], "restaurants": [], "is_valid": 1, "share_url": "http://www.zoma.to/r/0", "show_share_url": 0, "title": "Seev & the dreamers band Performing  Live ", "description": "#Sufi trans #Bollywood\t\t\t\t\r\n\t\t\t\t\r\n# rock your body\t\t\t\t\r\n\t\t\t\t\r\nand\t\t\t\t\r\n\t\t\t\t\r\nKick-start you weekend  on a high note as Seev & the dreamers band will be performing  live tonite @38 Barracks\t\t\t\t\r\n\t\t\t\t\r\n7.30 pm onwards\t\t\t\t\r\n\t\t\t\t\r\nFor booking contact -9717304097 /98\t\t\t\t", "display_time": "07:30 pm - 11:15 pm", "display_date": "18 January", "is_end_time_set": 1, "disclaimer": "Restaurants are solely responsible for the service; availability and quality of the events including all or any cancellations/ modifications/ complaints.", "event_category": 1, "event_category_name": "", "book_link": "", "types": [{"name": "Sufi Night", "color": "#6454B8"}, {"name": "Bollywood Night", "color": "#6454B8"}], "share_data": {"should_show": 0}}}, {"event": {"event_id": 294231, "friendly_start_date": "21 January", "friendly_end_date": "23 January", "friendly_timing_str": "Monday, 21st January - Wednesday, 23rd January", "start_date": "2019-01-21", "end_date": "2019-01-23", "end_time": "23:15:00", "start_time": "19:30:00", "is_active": 1, "date_added": "2019-01-02 12:56:17", "photos": [], "restaurants": [], "is_valid": 1, "share_url": "http://www.zoma.to/r/0", "show_share_url": 0, "title": "Shivam Luthra  performing  live ", "description": "Bollywood  night\r\nlet your monday Tuesday Wednesday be a rocking one as shivam luthra is performing live here 8:30 pm onwards\r\nfor booking contact- 9717304097/98", "display_time": "07:30 pm - 11:15 pm", "display_date": "21 January - 23 January", "is_end_time_set": 1, "disclaimer": "Restaurants are solely responsible for the service; availability and quality of the events including all or any cancellations/ modifications/ complaints.", "event_category": 1, "event_category_name": "", "book_link": "", "types": [{"name": "Solo Performance", "color": "#6454B8"}], "share_data": {"should_show": 0}}}, {"event": {"event_id": 250278, "friendly_start_date": "24 January", "friendly_end_date": "24 January", "friendly_timing_str": "Thursday, 24th January", "start_date": "2019-01-24", "end_date": "2019-01-24", "end_time": "23:15:00", "start_time": "19:30:00", "is_active": 1, "date_added": "2018-08-31 20:35:51", "photos": [{"photo": {"url": "https://b.zmtcdn.com/data/zomato_events/photos/d32/fbd9e05dfb6eb93b3dec1b314d3d8d32_1540970664.jpg", "thumb_url": "https://b.zmtcdn.com/data/zomato_events/photos/d32/fbd9e05dfb6eb93b3dec1b314d3d8d32_1540970664.jpg?fit=around%7C100%3A100&crop=100%3A100%3B%2A%2C%2A", "order": 0, "md5sum": "fbd9e05dfb6eb93b3dec1b314d3d8d32", "id": 367089, "photo_id": 367089, "uuid": 70657466450, "type": "FEATURED"}}], "restaurants": [], "is_valid": 1, "share_url": "http://www.zoma.to/r/0", "show_share_url": 0, "title": "Retro night  with Puneet Poddar ", "description": "Weekdays on a high note with the frequency  Puneet  poddar live here 7.30 pm onwards\t\t\r\nFor booking contact -9717304098/83\t\t", "display_time": "07:30 pm - 11:15 pm", "display_date": "24 January", "is_end_time_set": 1, "disclaimer": "Restaurants are solely responsible for the service; availability and quality of the events including all or any cancellations/ modifications/ complaints.", "event_category": 1, "event_category_name": "", "book_link": "", "types": [{"name": "Solo Performance", "color": "#6454B8"}], "share_data": {"should_show": 0}}}, {"event": {"event_id": 277575, "friendly_start_date": "25 January", "friendly_end_date": "25 January", "friendly_timing_str": "Friday, 25th January", "start_date": "2019-01-25", "end_date": "2019-01-25", "end_time": "23:15:00", "start_time": "19:30:00", "is_active": 1, "date_added": "2018-11-25 12:19:23", "photos": [{"photo": {"url": "https://b.zmtcdn.com/data/zomato_events/photos/0d2/49b2e4c149b0d3a68136ad4a833780d2_1543128563.jpg", "thumb_url": "https://b.zmtcdn.com/data/zomato_events/photos/0d2/49b2e4c149b0d3a68136ad4a833780d2_1543128563.jpg?fit=around%7C100%3A100&crop=100%3A100%3B%2A%2C%2A", "order": 0, "md5sum": "49b2e4c149b0d3a68136ad4a833780d2", "id": 376573, "photo_id": 376573, "uuid": 28554998368, "type": "FEATURED"}}], "restaurants": [], "is_valid": 1, "share_url": "http://www.zoma.to/r/0", "show_share_url": 0, "title": "Bollywood night with Seev the dreamers ", "description": "Bollywood  night\t\t\r\nLet your Saturday be a rocking one as Seev the Dreamers Band is performing  live here 7.30 pm onwards\t\t\r\nFor booking contact -9717304097/98/83", "display_time": "07:30 pm - 11:15 pm", "display_date": "25 January", "is_end_time_set": 1, "disclaimer": "Restaurants are solely responsible for the service; availability and quality of the events including all or any cancellations/ modifications/ complaints.", "event_category": 1, "event_category_name": "", "book_link": "", "types": [{"name": "Bollywood Night", "color": "#6454B8"}], "share_data": {"should_show": 0}}}, {"event": {"event_id": 250273, "friendly_start_date": "26 January", "friendly_end_date": "26 January", "friendly_timing_str": "Saturday, 26th January", "start_date": "2019-01-26", "end_date": "2019-01-26", "end_time": "23:15:00", "start_time": "19:30:00", "is_active": 1, "date_added": "2018-08-31 20:27:32", "photos": [{"photo": {"url": "https://b.zmtcdn.com/data/zomato_events/photos/f87/e275f52ea2e833f0d80de962d3251f87_1540970542.jpg", "thumb_url": "https://b.zmtcdn.com/data/zomato_events/photos/f87/e275f52ea2e833f0d80de962d3251f87_1540970542.jpg?fit=around%7C100%3A100&crop=100%3A100%3B%2A%2C%2A", "order": 0, "md5sum": "e275f52ea2e833f0d80de962d3251f87", "id": 367087, "photo_id": 367087, "uuid": 7053856585, "type": "FEATURED"}}], "restaurants": [], "is_valid": 1, "share_url": "http://www.zoma.to/r/0", "show_share_url": 0, "title": "Zehan the band Performing  Live ", "description": "#Sufi trans #Bollywood\t\t\t\t\r\n\t\t\t\t\r\n# rock your body\t\t\t\t\r\n\t\t\t\t\r\nand\t\t\t\t\r\n\t\t\t\t\r\nKick-start you weekend  on a high note as Zehan the band will be performing  live tonite @38 Barracks\t\t\t\t\r\n\t\t\t\t\r\n7.30 pm onwards\t\t\t\t\r\n\t\t\t\t\r\nFor booking contact -9717304097 /98\t\t\t\t", "display_time": "07:30 pm - 11:15 pm", "display_date": "26 January", "is_end_time_set": 1, "disclaimer": "Restaurants are solely responsible for the service; availability and quality of the events including all or any cancellations/ modifications/ complaints.", "event_category": 1, "event_category_name": "", "book_link": "", "types": [{"name": "Bollywood Night", "color": "#6454B8"}, {"name": "Sufi Night", "color": "#6454B8"}], "share_data": {"should_show": 0}}}, {"event": {"event_id": 294235, "friendly_start_date": "28 January", "friendly_end_date": "30 January", "friendly_timing_str": "Monday, 28th January - Wednesday, 30th January", "start_date": "2019-01-28", "end_date": "2019-01-30", "end_time": "17:30:00", "start_time": "14:00:00", "is_active": 1, "date_added": "2019-01-02 12:58:28", "photos": [{"photo": {"url": "https://b.zmtcdn.com/data/zomato_events/photos/f09/c2f7ee8d7a2ab9e19b9b86938983bf09_1534917842.jpeg", "thumb_url": "https://b.zmtcdn.com/data/zomato_events/photos/f09/c2f7ee8d7a2ab9e19b9b86938983bf09_1534917842.jpeg?fit=around%7C100%3A100&crop=100%3A100%3B%2A%2C%2A", "order": 0, "md5sum": "c2f7ee8d7a2ab9e19b9b86938983bf09", "id": 397634, "photo_id": 397634, "uuid": 14107790391, "type": "NORMAL"}}], "restaurants": [], "is_valid": 1, "share_url": "http://www.zoma.to/r/0", "show_share_url": 0, "title": "Shivam Luthra  performing  live ", "description": "Bollywood  night\r\nlet your Monday Tuesday Wednesday be a rocking one as shivam luthra is performing live here 7:30 pm onwards\r\nfor booking contact- 9717304097/98", "display_time": "02:00 pm - 05:30 pm", "display_date": "28 January - 30 January", "is_end_time_set": 1, "disclaimer": "Restaurants are solely responsible for the service; availability and quality of the events including all or any cancellations/ modifications/ complaints.", "event_category": 1, "event_category_name": "", "book_link": "", "types": [{"name": "Solo Performance", "color": "#6454B8"}], "share_data": {"should_show": 0}}}, {"event": {"event_id": 176860, "friendly_start_date": "31 January", "friendly_end_date": "31 January", "friendly_timing_str": "Thursday, 31st January", "start_date": "2019-01-31", "end_date": "2019-01-31", "end_time": "23:30:00", "start_time": "19:30:00", "is_active": 1, "date_added": "2017-12-14 05:50:15", "photos": [{"photo": {"url": "https://b.zmtcdn.com/data/zomato_events/photos/9f3/09525327b65558f76dc126cbcb79b9f3_1525936586.jpg", "thumb_url": "https://b.zmtcdn.com/data/zomato_events/photos/9f3/09525327b65558f76dc126cbcb79b9f3_1525936586.jpg?fit=around%7C100%3A100&crop=100%3A100%3B%2A%2C%2A", "order": 0, "md5sum": "09525327b65558f76dc126cbcb79b9f3", "id": 304200, "photo_id": 304200, "uuid": 36584248712, "type": "FEATURED"}}], "restaurants": [], "is_valid": 1, "share_url": "http://www.zoma.to/r/0", "show_share_url": 0, "title": "Retro night with Puneet poddar  @38 Barracks", "description": "Weekdays  on a high note with the frequency  Puneet poddar live here 8.30 pm onwards  \r\nFor booking contact -9717304097/98", "display_time": "07:30 pm - 11:30 pm", "display_date": "31 January", "is_end_time_set": 1, "disclaimer": "Restaurants are solely responsible for the service; availability and quality of the events including all or any cancellations/ modifications/ complaints.", "event_category": 1, "event_category_name": "", "book_link": "", "types": [{"name": "Solo Performance", "color": "#6454B8"}], "share_data": {"should_show": 0}}}, {"event": {"event_id": 294229, "friendly_start_date": "11 February", "friendly_end_date": "13 February", "friendly_timing_str": "Monday, 11th February - Wednesday, 13th February", "start_date": "2019-02-11", "end_date": "2019-02-13", "end_time": "17:30:00", "start_time": "14:00:00", "is_active": 1, "date_added": "2019-01-02 12:54:52", "photos": [{"photo": {"url": "https://b.zmtcdn.com/data/zomato_events/photos/f09/c2f7ee8d7a2ab9e19b9b86938983bf09_1534917842.jpeg", "thumb_url": "https://b.zmtcdn.com/data/zomato_events/photos/f09/c2f7ee8d7a2ab9e19b9b86938983bf09_1534917842.jpeg?fit=around%7C100%3A100&crop=100%3A100%3B%2A%2C%2A", "order": 0, "md5sum": "c2f7ee8d7a2ab9e19b9b86938983bf09", "id": 397629, "photo_id": 397629, "uuid": 13891353637, "type": "NORMAL"}}], "restaurants": [], "is_valid": 1, "share_url": "http://www.zoma.to/r/0", "show_share_url": 0, "title": "Shivam Luthra  performing  live ", "description": "Bollywood  night\r\nlet your   rocking one as shivam luthra is performing live here 2\n7:30 pm onwards\r\nfor booking contact- 9717304097/98", "display_time": "02:00 pm - 05:30 pm", "display_date": "11 February - 13 February", "is_end_time_set": 1, "disclaimer": "Restaurants are solely responsible for the service; availability and quality of the events including all or any cancellations/ modifications/ complaints.", "event_category": 1, "event_category_name": "", "book_link": "", "types": [{"name": "Solo Performance", "color": "#6454B8"}], "share_data": {"should_show": 0}}}], "opentable_support": 0, "is_zomato_book_res": 0, "mezzo_provider": "OTHER", "is_book_form_web_view": 0, "book_form_web_view_url": "", "book_again_url": "", "thumb": "https://b.zmtcdn.com/data/res_imagery/18241537_RESTAURANT_7ba7c3b1b8be194439a2e2a2de861c0c.jpg?fit=around%7C200%3A200&crop=200%3A200%3B%2A%2C%2A", "user_rating": {"aggregate_rating": "4.8", "rating_text": "Excellent", "rating_color": "3F7E00", "votes": "2806"}, "photos_url": "https://www.zomato.com/ncr/38-barracks-connaught-place-new-delhi/photos?utm_source=api_basic_user&utm_medium=api&utm_campaign=v2.1#tabtop", "menu_url": "https://www.zomato.com/ncr/38-barracks-connaught-place-new-delhi/menu?utm_source=api_basic_user&utm_medium=api&utm_campaign=v2.1&openSwipeBox=menu&showMinimal=1#tabtop", "featured_image": "https://b.zmtcdn.com/data/res_imagery/18241537_RESTAURANT_7ba7c3b1b8be194439a2e2a2de861c0c.jpg?output-format=webp", "medio_provider": 1, "has_online_delivery": 1, "is_delivering_now": 0, "include_bogo_offers": true, "deeplink": "zomato://restaurant/18241537", "is_table_reservation_supported": 1, "has_table_booking": 0, "events_url": "https://www.zomato.com/ncr/38-barracks-connaught-place-new-delhi/events#tabtop?utm_source=api_basic_user&utm_medium=api&utm_campaign=v2.1", "establishment_types": []}}, {"restaurant": {"R": {"res_id": 18696790}, "apikey": "745c5f1b6907194a76b81269f31e9046", "id": "18696790", "name": "MVs Wraps & Bowls", "url": "https://www.zomato.com/ncr/mvs-wraps-bowls-indirapuram-ghaziabad?utm_source=api_basic_user&utm_medium=api&utm_campaign=v2.1", "location": {"address": "C-106, Upper Ground Floor, OC Square, Ahinsa Khand 1, Indirapuram, Ghaziabad", "locality": "Indirapuram", "city": "Ghaziabad", "city_id": 1, "latitude": "28.6391720961", "longitude": "77.3617888615", "zipcode": "", "country_id": 1, "locality_verbose": "Indirapuram, Ghaziabad"}, "switch_to_order_menu": 0, "cuisines": "Mexican", "average_cost_for_two": 300, "price_range": 1, "currency": "Rs.", "offers": [], "opentable_support": 0, "is_zomato_book_res": 0, "mezzo_provider": "OTHER", "is_book_form_web_view": 0, "book_form_web_view_url": "", "book_again_url": "", "thumb": "", "user_rating": {"aggregate_rating": "3.6", "rating_text": "Good", "rating_color": "9ACD32", "votes": "35"}, "photos_url": "https://www.zomato.com/ncr/mvs-wraps-bowls-indirapuram-ghaziabad/photos?utm_source=api_basic_user&utm_medium=api&utm_campaign=v2.1#tabtop", "menu_url": "https://www.zomato.com/ncr/mvs-wraps-bowls-indirapuram-ghaziabad/menu?utm_source=api_basic_user&utm_medium=api&utm_campaign=v2.1&openSwipeBox=menu&showMinimal=1#tabtop", "featured_image": "", "has_online_delivery": 1, "is_delivering_now": 0, "include_bogo_offers": true, "deeplink": "zomato://restaurant/18696790", "is_table_reservation_supported": 0, "has_table_booking": 0, "events_url": "https://www.zomato.com/ncr/mvs-wraps-bowls-indirapuram-ghaziabad/events#tabtop?utm_source=api_basic_user&utm_medium=api&utm_campaign=v2.1", "establishment_types": []}}, {"restaurant": {"R": {"res_id": 18649486}, "apikey": "745c5f1b6907194a76b81269f31e9046", "id": "18649486", "name": "The Drunken Botanist", "url": "https://www.zomato.com/ncr/the-drunken-botanist-dlf-cyber-city-gurgaon?utm_source=api_basic_user&utm_medium=api&utm_campaign=v2.1", "location": {"address": "Unit 1B & 1C, Upper Ground Floor-C, Building 10C, Cyber Hub, DLF Cyber City, Gurgaon", "locality": "Cyber Hub, DLF Cyber City", "city": "Gurgaon", "city_id": 1, "latitude": "28.4936741035", "longitude": "77.0883342996", "zipcode": "", "country_id": 1, "locality_verbose": "Cyber Hub, DLF Cyber City, Gurgaon"}, "switch_to_order_menu": 0, "cuisines": "Continental, Italian, Chinese, North Indian, Momos", "average_cost_for_two": 1500, "price_range": 3, "currency": "Rs.", "offers": [], "opentable_support": 0, "is_zomato_book_res": 0, "mezzo_provider": "OTHER", "is_book_form_web_view": 0, "book_form_web_view_url": "", "book_again_url": "", "thumb": "https://b.zmtcdn.com/data/pictures/6/18649486/891f5711b0028057cdf834ca1fee9780.jpg?fit=around%7C200%3A200&crop=200%3A200%3B%2A%2C%2A", "user_rating": {"aggregate_rating": "4.3", "rating_text": "Very Good", "rating_color": "5BA829", "votes": "3916"}, "photos_url": "https://www.zomato.com/ncr/the-drunken-botanist-dlf-cyber-city-gurgaon/photos?utm_source=api_basic_user&utm_medium=api&utm_campaign=v2.1#tabtop", "menu_url": "https://www.zomato.com/ncr/the-drunken-botanist-dlf-cyber-city-gurgaon/menu?utm_source=api_basic_user&utm_medium=api&utm_campaign=v2.1&openSwipeBox=menu&showMinimal=1#tabtop", "featured_image": "https://b.zmtcdn.com/data/pictures/6/18649486/891f5711b0028057cdf834ca1fee9780.jpg?output-format=webp", "has_online_delivery": 0, "is_delivering_now": 0, "include_bogo_offers": true, "deeplink": "zomato://restaurant/18649486", "is_table_reservation_supported": 0, "has_table_booking": 0, "events_url": "https://www.zomato.com/ncr/the-drunken-botanist-dlf-cyber-city-gurgaon/events#tabtop?utm_source=api_basic_user&utm_medium=api&utm_campaign=v2.1", "establishment_types": []}}, {"restaurant": {"R": {"res_id": 308322}, "apikey": "745c5f1b6907194a76b81269f31e9046", "id": "308322", "name": "Hauz Khas Social", "url": "https://www.zomato.com/HauzKhasSocial?utm_source=api_basic_user&utm_medium=api&utm_campaign=v2.1", "location": {"address": "9-A & 12, Hauz Khas Village, New Delhi", "locality": "Hauz Khas Village", "city": "New Delhi", "city_id": 1, "latitude": "28.5542935327", "longitude": "77.1944381297", "zipcode": "", "country_id": 1, "locality_verbose": "Hauz Khas Village, New Delhi"}, "switch_to_order_menu": 0, "cuisines": "Continental, American, Asian, North Indian", "average_cost_for_two": 1300, "price_range": 3, "currency": "Rs.", "offers": [], "opentable_support": 0, "is_zomato_book_res": 0, "mezzo_provider": "OTHER", "is_book_form_web_view": 0, "book_form_web_view_url": "", "book_again_url": "", "thumb": "https://b.zmtcdn.com/data/pictures/2/308322/b5221a35591a8f709a2cf34e8f4bb86b.jpg?fit=around%7C200%3A200&crop=200%3A200%3B%2A%2C%2A", "user_rating": {"aggregate_rating": "4.7", "rating_text": "Excellent", "rating_color": "3F7E00", "votes": "12498"}, "photos_url": "https://www.zomato.com/HauzKhasSocial/photos?utm_source=api_basic_user&utm_medium=api&utm_campaign=v2.1#tabtop", "menu_url": "https://www.zomato.com/HauzKhasSocial/menu?utm_source=api_basic_user&utm_medium=api&utm_campaign=v2.1&openSwipeBox=menu&showMinimal=1#tabtop", "featured_image": "https://b.zmtcdn.com/data/pictures/2/308322/b5221a35591a8f709a2cf34e8f4bb86b.jpg", "medio_provider": 1, "has_online_delivery": 1, "is_delivering_now": 0, "include_bogo_offers": true, "deeplink": "zomato://restaurant/308322", "is_table_reservation_supported": 1, "has_table_booking": 0, "events_url": "https://www.zomato.com/HauzKhasSocial/events#tabtop?utm_source=api_basic_user&utm_medium=api&utm_campaign=v2.1", "establishment_types": []}}, {"restaurant": {"R": {"res_id": 18355419}, "apikey": "745c5f1b6907194a76b81269f31e9046", "id": "18355419", "name": "Nachos And Company", "url": "https://www.zomato.com/ncr/nachos-and-company-green-park-new-delhi?utm_source=api_basic_user&utm_medium=api&utm_campaign=v2.1", "location": {"address": "L-1, 3rd Floor, Green Park Extension, Green Park, New Delhi", "locality": "Green Park", "city": "New Delhi", "city_id": 1, "latitude": "28.5607845000", "longitude": "77.2015772000", "zipcode": "110029", "country_id": 1, "locality_verbose": "Green Park, New Delhi"}, "switch_to_order_menu": 0, "cuisines": "Mexican", "average_cost_for_two": 700, "price_range": 2, "currency": "Rs.", "offers": [], "opentable_support": 0, "is_zomato_book_res": 0, "mezzo_provider": "OTHER", "is_book_form_web_view": 0, "book_form_web_view_url": "", "book_again_url": "", "thumb": "https://b.zmtcdn.com/data/res_imagery/18355419_RESTAURANT_695be386eb91438cf711a55e810aee56.jpg?fit=around%7C200%3A200&crop=200%3A200%3B%2A%2C%2A", "user_rating": {"aggregate_rating": "3.4", "rating_text": "Average", "rating_color": "CDD614", "votes": "14"}, "photos_url": "https://www.zomato.com/ncr/nachos-and-company-green-park-new-delhi/photos?utm_source=api_basic_user&utm_medium=api&utm_campaign=v2.1#tabtop", "menu_url": "https://www.zomato.com/ncr/nachos-and-company-green-park-new-delhi/menu?utm_source=api_basic_user&utm_medium=api&utm_campaign=v2.1&openSwipeBox=menu&showMinimal=1#tabtop", "featured_image": "https://b.zmtcdn.com/data/res_imagery/18355419_RESTAURANT_695be386eb91438cf711a55e810aee56.jpg", "has_online_delivery": 0, "is_delivering_now": 0, "include_bogo_offers": true, "deeplink": "zomato://restaurant/18355419", "is_table_reservation_supported": 0, "has_table_booking": 0, "events_url": "https://www.zomato.com/ncr/nachos-and-company-green-park-new-delhi/events#tabtop?utm_source=api_basic_user&utm_medium=api&utm_campaign=v2.1", "establishment_types": []}}, {"restaurant": {"R": {"res_id": 18715973}, "apikey": "745c5f1b6907194a76b81269f31e9046", "id": "18715973", "name": "Shoney's Cafe", "url": "https://www.zomato.com/ncr/shoneys-cafe-dlf-phase-4-gurgaon?utm_source=api_basic_user&utm_medium=api&utm_campaign=v2.1", "location": {"address": "SF 101, First Floor, Galleria Market, DLF Phase 4, Gurgaon", "locality": "DLF Phase 4", "city": "Gurgaon", "city_id": 1, "latitude": "28.4675406504", "longitude": "77.0814597979", "zipcode": "", "country_id": 1, "locality_verbose": "DLF Phase 4, Gurgaon"}, "switch_to_order_menu": 0, "cuisines": "Mexican, Lebanese", "average_cost_for_two": 400, "price_range": 1, "currency": "Rs.", "offers": [], "opentable_support": 0, "is_zomato_book_res": 0, "mezzo_provider": "OTHER", "is_book_form_web_view": 0, "book_form_web_view_url": "", "book_again_url": "", "thumb": "", "user_rating": {"aggregate_rating": "3.1", "rating_text": "Average", "rating_color": "CDD614", "votes": 4}, "photos_url": "https://www.zomato.com/ncr/shoneys-cafe-dlf-phase-4-gurgaon/photos?utm_source=api_basic_user&utm_medium=api&utm_campaign=v2.1#tabtop", "menu_url": "https://www.zomato.com/ncr/shoneys-cafe-dlf-phase-4-gurgaon/menu?utm_source=api_basic_user&utm_medium=api&utm_campaign=v2.1&openSwipeBox=menu&showMinimal=1#tabtop", "featured_image": "", "has_online_delivery": 1, "is_delivering_now": 0, "include_bogo_offers": true, "deeplink": "zomato://restaurant/18715973", "is_table_reservation_supported": 0, "has_table_booking": 0, "events_url": "https://www.zomato.com/ncr/shoneys-cafe-dlf-phase-4-gurgaon/events#tabtop?utm_source=api_basic_user&utm_medium=api&utm_campaign=v2.1", "establishment_types": []}}, {"restaurant": {"R": {"res_id": 18238278}, "apikey": "745c5f1b6907194a76b81269f31e9046", "id": "18238278", "name": "Tamasha", "url": "https://www.zomato.com/ncr/tamasha-connaught-place-new-delhi?utm_source=api_basic_user&utm_medium=api&utm_campaign=v2.1", "location": {"address": "28, Block A, Kasturba Gandhi Marg, Connaught Place, New Delhi", "locality": "Connaught Place", "city": "New Delhi", "city_id": 1, "latitude": "28.6296624581", "longitude": "77.2218600288", "zipcode": "110001", "country_id": 1, "locality_verbose": "Connaught Place, New Delhi"}, "switch_to_order_menu": 0, "cuisines": "Finger Food, North Indian, Continental, Italian", "average_cost_for_two": 1600, "price_range": 3, "currency": "Rs.", "offers": [], "opentable_support": 0, "is_zomato_book_res": 0, "mezzo_provider": "OTHER", "is_book_form_web_view": 0, "book_form_web_view_url": "", "book_again_url": "", "thumb": "https://b.zmtcdn.com/data/pictures/8/18238278/39d09a5c0215d8b12ae4742efe564a62.png?fit=around%7C200%3A200&crop=200%3A200%3B%2A%2C%2A", "user_rating": {"aggregate_rating": "4.4", "rating_text": "Very Good", "rating_color": "5BA829", "votes": "6870"}, "photos_url": "https://www.zomato.com/ncr/tamasha-connaught-place-new-delhi/photos?utm_source=api_basic_user&utm_medium=api&utm_campaign=v2.1#tabtop", "menu_url": "https://www.zomato.com/ncr/tamasha-connaught-place-new-delhi/menu?utm_source=api_basic_user&utm_medium=api&utm_campaign=v2.1&openSwipeBox=menu&showMinimal=1#tabtop", "featured_image": "https://b.zmtcdn.com/data/pictures/8/18238278/39d09a5c0215d8b12ae4742efe564a62.png", "has_online_delivery": 0, "is_delivering_now": 0, "include_bogo_offers": true, "deeplink": "zomato://restaurant/18238278", "is_table_reservation_supported": 0, "has_table_booking": 0, "events_url": "https://www.zomato.com/ncr/tamasha-connaught-place-new-delhi/events#tabtop?utm_source=api_basic_user&utm_medium=api&utm_campaign=v2.1", "establishment_types": []}}, {"restaurant": {"R": {"res_id": 18382360}, "apikey": "745c5f1b6907194a76b81269f31e9046", "id": "18382360", "name": "Local", "url": "https://www.zomato.com/ncr/local-connaught-place-new-delhi?utm_source=api_basic_user&utm_medium=api&utm_campaign=v2.1", "location": {"address": "11, KG Marg, Scindia House, Connaught Place, New Delhi", "locality": "Connaught Place", "city": "New Delhi", "city_id": 1, "latitude": "28.6299140703", "longitude": "77.2211713716", "zipcode": "110001", "country_id": 1, "locality_verbose": "Connaught Place, New Delhi"}, "switch_to_order_menu": 0, "cuisines": "North Indian, Continental, Momos", "average_cost_for_two": 1600, "price_range": 3, "currency": "Rs.", "offers": [], "opentable_support": 0, "is_zomato_book_res": 0, "mezzo_provider": "OTHER", "is_book_form_web_view": 0, "book_form_web_view_url": "", "book_again_url": "", "thumb": "https://b.zmtcdn.com/data/pictures/0/18382360/e573a272f5e7b1d7b40a5eb6da62f562.jpg?fit=around%7C200%3A200&crop=200%3A200%3B%2A%2C%2A", "user_rating": {"aggregate_rating": "4.3", "rating_text": "Very Good", "rating_color": "5BA829", "votes": "4811"}, "photos_url": "https://www.zomato.com/ncr/local-connaught-place-new-delhi/photos?utm_source=api_basic_user&utm_medium=api&utm_campaign=v2.1#tabtop", "menu_url": "https://www.zomato.com/ncr/local-connaught-place-new-delhi/menu?utm_source=api_basic_user&utm_medium=api&utm_campaign=v2.1&openSwipeBox=menu&showMinimal=1#tabtop", "featured_image": "https://b.zmtcdn.com/data/pictures/0/18382360/e573a272f5e7b1d7b40a5eb6da62f562.jpg?output-format=webp", "medio_provider": 1, "has_online_delivery": 0, "is_delivering_now": 0, "include_bogo_offers": true, "deeplink": "zomato://restaurant/18382360", "is_table_reservation_supported": 1, "has_table_booking": 0, "events_url": "https://www.zomato.com/ncr/local-connaught-place-new-delhi/events#tabtop?utm_source=api_basic_user&utm_medium=api&utm_campaign=v2.1", "establishment_types": []}}, {"restaurant": {"R": {"res_id": 18418277}, "apikey": "745c5f1b6907194a76b81269f31e9046", "id": "18418277", "name": "Ministry Of Beer", "url": "https://www.zomato.com/ncr/ministry-of-beer-connaught-place-new-delhi?utm_source=api_basic_user&utm_medium=api&utm_campaign=v2.1", "location": {"address": "M 43, Outer Circle, Connaught Place, New Delhi", "locality": "Connaught Place", "city": "New Delhi", "city_id": 1, "latitude": "28.6332862038", "longitude": "77.2227874026", "zipcode": "110001", "country_id": 1, "locality_verbose": "Connaught Place, New Delhi"}, "switch_to_order_menu": 0, "cuisines": "Continental, Italian, Asian, Indian, Momos", "average_cost_for_two": 1500, "price_range": 3, "currency": "Rs.", "offers": [], "zomato_events": [{"event": {"event_id": 295537, "friendly_start_date": "13 January", "friendly_end_date": "13 January", "friendly_timing_str": "Sunday, 13th January", "start_date": "2019-01-13", "end_date": "2019-01-13", "end_time": "17:00:00", "start_time": "12:00:00", "is_active": 1, "date_added": "2019-01-04 19:37:16", "photos": [], "restaurants": [], "is_valid": 1, "share_url": "http://www.zoma.to/r/0", "show_share_url": 0, "title": "Sunday Brunch", "description": "Nothing better than a food coma on a Sunday noon! Join us to gorge on scrumptious dishes with chilled beer and sparkling wine. \nFor reservations, call: +91 8800012060 | +91 8800012061", "display_time": "12:00 pm - 05:00 pm", "display_date": "13 January", "is_end_time_set": 1, "disclaimer": "Restaurants are solely responsible for the service; availability and quality of the events including all or any cancellations/ modifications/ complaints.", "event_category": 0, "event_category_name": "", "book_link": "", "types": [], "share_data": {"should_show": 0}}}, {"event": {"event_id": 297218, "friendly_start_date": "13 January", "friendly_end_date": "13 January", "friendly_timing_str": "Sunday, 13th January", "start_date": "2019-01-13", "end_date": "2019-01-13", "end_time": "23:55:00", "start_time": "20:00:00", "is_active": 1, "date_added": "2019-01-09 11:45:15", "photos": [{"photo": {"url": "https://b.zmtcdn.com/data/zomato_events/photos/8e4/055915ddc81dbe7fc20c0d344ac218e4_1547014515.png", "thumb_url": "https://b.zmtcdn.com/data/zomato_events/photos/8e4/055915ddc81dbe7fc20c0d344ac218e4_1547014515.png?fit=around%7C100%3A100&crop=100%3A100%3B%2A%2C%2A", "order": 0, "md5sum": "055915ddc81dbe7fc20c0d344ac218e4", "id": 401204, "photo_id": 401204, "uuid": 1547014502201561, "type": "NORMAL"}}], "restaurants": [], "is_valid": 1, "share_url": "http://www.zoma.to/r/0", "show_share_url": 0, "title": "Lohri at MOB ", "description": "Dance your heart out with Russian Dholis playing LED dhols just for you! Treat your palate with the finest and most delicious treats and get high on happiness with us!", "display_time": "08:00 pm - 11:55 pm", "display_date": "13 January", "is_end_time_set": 1, "disclaimer": "Restaurants are solely responsible for the service; availability and quality of the events including all or any cancellations/ modifications/ complaints.", "event_category": 0, "event_category_name": "", "book_link": "", "types": [{"name": "Live DJ", "color": "#6454B8"}], "share_data": {"should_show": 0}}}, {"event": {"event_id": 295542, "friendly_start_date": "17 January", "friendly_end_date": "17 January", "friendly_timing_str": "Thursday, 17th January", "start_date": "2019-01-17", "end_date": "2019-01-17", "end_time": "23:55:00", "start_time": "21:00:00", "is_active": 1, "date_added": "2019-01-04 19:44:41", "photos": [], "restaurants": [], "is_valid": 1, "share_url": "http://www.zoma.to/r/0", "show_share_url": 0, "title": "Girlfriend's Night", "description": "Enjoy unlimited cocktails and dimsums, have a fun night out with your girlfriends every Thursday!\nFor reservations, call: +91 8800012060 | +91 8800012061", "display_time": "09:00 pm - 11:55 pm", "display_date": "17 January", "is_end_time_set": 1, "disclaimer": "Restaurants are solely responsible for the service; availability and quality of the events including all or any cancellations/ modifications/ complaints.", "event_category": 0, "event_category_name": "", "book_link": "", "types": [], "share_data": {"should_show": 0}}}, {"event": {"event_id": 296442, "friendly_start_date": "19 January", "friendly_end_date": "19 January", "friendly_timing_str": "Saturday, 19th January", "start_date": "2019-01-19", "end_date": "2019-01-19", "end_time": "23:55:00", "start_time": "21:00:00", "is_active": 1, "date_added": "2019-01-07 18:38:35", "photos": [], "restaurants": [], "is_valid": 1, "share_url": "http://www.zoma.to/r/0", "show_share_url": 0, "title": "ShaniBar Night ", "description": "Put on your dancing shoes and get ready to sway to the tunes of DJ Sam every Saturday with us.\nFor reservations, call: +91 8800012060 | +91 8800012061", "display_time": "09:00 pm - 11:55 pm", "display_date": "19 January", "is_end_time_set": 1, "disclaimer": "Restaurants are solely responsible for the service; availability and quality of the events including all or any cancellations/ modifications/ complaints.", "event_category": 0, "event_category_name": "", "book_link": "", "types": [{"name": "Live DJ", "color": "#6454B8"}], "share_data": {"should_show": 0}}}, {"event": {"event_id": 295538, "friendly_start_date": "20 January", "friendly_end_date": "20 January", "friendly_timing_str": "Sunday, 20th January", "start_date": "2019-01-20", "end_date": "2019-01-20", "end_time": "17:00:00", "start_time": "12:00:00", "is_active": 1, "date_added": "2019-01-04 19:38:09", "photos": [], "restaurants": [], "is_valid": 1, "share_url": "http://www.zoma.to/r/0", "show_share_url": 0, "title": "Sunday Brunch", "description": "Nothing better than a food coma on a Sunday noon! Join us to gorge on scrumptious dishes with chilled beer and sparkling wine. \nFor reservations, call: +91 8800012060 | +91 8800012061", "display_time": "12:00 pm - 05:00 pm", "display_date": "20 January", "is_end_time_set": 1, "disclaimer": "Restaurants are solely responsible for the service; availability and quality of the events including all or any cancellations/ modifications/ complaints.", "event_category": 0, "event_category_name": "", "book_link": "", "types": [], "share_data": {"should_show": 0}}}, {"event": {"event_id": 295546, "friendly_start_date": "24 January", "friendly_end_date": "24 January", "friendly_timing_str": "Thursday, 24th January", "start_date": "2019-01-24", "end_date": "2019-01-24", "end_time": "23:55:00", "start_time": "21:00:00", "is_active": 1, "date_added": "2019-01-04 19:47:39", "photos": [], "restaurants": [], "is_valid": 1, "share_url": "http://www.zoma.to/r/0", "show_share_url": 0, "title": "Girlfriend's Night", "description": "Enjoy unlimited cocktails and dimsums, have a fun night out with your girlfriends every Thursday!\nFor reservations, call: +91 8800012060 | +91 8800012061", "display_time": "09:00 pm - 11:55 pm", "display_date": "24 January", "is_end_time_set": 1, "disclaimer": "Restaurants are solely responsible for the service; availability and quality of the events including all or any cancellations/ modifications/ complaints.", "event_category": 0, "event_category_name": "", "book_link": "", "types": [], "share_data": {"should_show": 0}}}, {"event": {"event_id": 296446, "friendly_start_date": "26 January", "friendly_end_date": "26 January", "friendly_timing_str": "Saturday, 26th January", "start_date": "2019-01-26", "end_date": "2019-01-26", "end_time": "23:55:00", "start_time": "21:00:00", "is_active": 1, "date_added": "2019-01-07 18:41:39", "photos": [], "restaurants": [], "is_valid": 1, "share_url": "http://www.zoma.to/r/0", "show_share_url": 0, "title": "ShaniBar Night ", "description": "Put on your dancing shoes and get ready to sway to the tunes of DJ Sam every Saturday with us.\nFor reservations, call: +91 8800012060 | +91 8800012061", "display_time": "09:00 pm - 11:55 pm", "display_date": "26 January", "is_end_time_set": 1, "disclaimer": "Restaurants are solely responsible for the service; availability and quality of the events including all or any cancellations/ modifications/ complaints.", "event_category": 0, "event_category_name": "", "book_link": "", "types": [{"name": "Live DJ", "color": "#6454B8"}], "share_data": {"should_show": 0}}}, {"event": {"event_id": 295539, "friendly_start_date": "27 January", "friendly_end_date": "27 January", "friendly_timing_str": "Sunday, 27th January", "start_date": "2019-01-27", "end_date": "2019-01-27", "end_time": "17:00:00", "start_time": "12:00:00", "is_active": 1, "date_added": "2019-01-04 19:39:13", "photos": [], "restaurants": [], "is_valid": 1, "share_url": "http://www.zoma.to/r/0", "show_share_url": 0, "title": "Sunday Brunch", "description": "Nothing better than a food coma on a Sunday noon! Join us to gorge on scrumptious dishes with chilled beer and sparkling wine. \nFor reservations, call: +91 8800012060 | +91 8800012061", "display_time": "12:00 pm - 05:00 pm", "display_date": "27 January", "is_end_time_set": 1, "disclaimer": "Restaurants are solely responsible for the service; availability and quality of the events including all or any cancellations/ modifications/ complaints.", "event_category": 0, "event_category_name": "", "book_link": "", "types": [], "share_data": {"should_show": 0}}}, {"event": {"event_id": 295547, "friendly_start_date": "31 January", "friendly_end_date": "31 January", "friendly_timing_str": "Thursday, 31st January", "start_date": "2019-01-31", "end_date": "2019-01-31", "end_time": "23:55:00", "start_time": "21:00:00", "is_active": 1, "date_added": "2019-01-04 19:48:52", "photos": [], "restaurants": [], "is_valid": 1, "share_url": "http://www.zoma.to/r/0", "show_share_url": 0, "title": "Girlfriend's Night ", "description": "Enjoy unlimited cocktails and dimsums, have a fun night out with your girlfriends every Thursday!\nFor reservations, call: +91 8800012060 | +91 8800012061", "display_time": "09:00 pm - 11:55 pm", "display_date": "31 January", "is_end_time_set": 1, "disclaimer": "Restaurants are solely responsible for the service; availability and quality of the events including all or any cancellations/ modifications/ complaints.", "event_category": 0, "event_category_name": "", "book_link": "", "types": [], "share_data": {"should_show": 0}}}], "opentable_support": 0, "is_zomato_book_res": 0, "mezzo_provider": "OTHER", "is_book_form_web_view": 0, "book_form_web_view_url": "", "book_again_url": "", "thumb": "https://b.zmtcdn.com/data/pictures/7/18418277/844c3a3fbaaf85ae19831c502800ddbd.jpg?fit=around%7C200%3A200&crop=200%3A200%3B%2A%2C%2A", "user_rating": {"aggregate_rating": "4.6", "rating_text": "Excellent", "rating_color": "3F7E00", "votes": "2629"}, "photos_url": "https://www.zomato.com/ncr/ministry-of-beer-connaught-place-new-delhi/photos?utm_source=api_basic_user&utm_medium=api&utm_campaign=v2.1#tabtop", "menu_url": "https://www.zomato.com/ncr/ministry-of-beer-connaught-place-new-delhi/menu?utm_source=api_basic_user&utm_medium=api&utm_campaign=v2.1&openSwipeBox=menu&showMinimal=1#tabtop", "featured_image": "https://b.zmtcdn.com/data/pictures/7/18418277/844c3a3fbaaf85ae19831c502800ddbd.jpg?output-format=webp", "medio_provider": 1, "has_online_delivery": 0, "is_delivering_now": 0, "include_bogo_offers": true, "deeplink": "zomato://restaurant/18418277", "is_table_reservation_supported": 1, "has_table_booking": 0, "events_url": "https://www.zomato.com/ncr/ministry-of-beer-connaught-place-new-delhi/events#tabtop?utm_source=api_basic_user&utm_medium=api&utm_campaign=v2.1", "establishment_types": []}}, {"restaurant": {"R": {"res_id": 18759923}, "apikey": "745c5f1b6907194a76b81269f31e9046", "id": "18759923", "name": "Duty Free | Vayu Bar", "url": "https://www.zomato.com/ncr/duty-free-vayu-bar-sector-29-gurgaon?utm_source=api_basic_user&utm_medium=api&utm_campaign=v2.1", "location": {"address": "SCO 32, Sector 29, Gurgaon", "locality": "Sector 29", "city": "Gurgaon", "city_id": 1, "latitude": "28.4683517635", "longitude": "77.0627641305", "zipcode": "", "country_id": 1, "locality_verbose": "Sector 29, Gurgaon"}, "switch_to_order_menu": 0, "cuisines": "Continental, Mexican, North Indian, Italian, Asian", "average_cost_for_two": 1300, "price_range": 3, "currency": "Rs.", "offers": [], "zomato_events": [{"event": {"event_id": 296972, "friendly_start_date": "08 January", "friendly_end_date": "31 January", "friendly_timing_str": "Tuesday, 8th January - Thursday, 31st January", "start_date": "2019-01-08", "end_date": "2019-01-31", "end_time": "23:00:00", "start_time": "20:00:00", "is_active": 1, "date_added": "2019-01-08 17:46:52", "photos": [{"photo": {"url": "https://b.zmtcdn.com/data/zomato_events/photos/6f3/858beffe30c863d7232e69bdfc76f6f3_1546949844.jpeg", "thumb_url": "https://b.zmtcdn.com/data/zomato_events/photos/6f3/858beffe30c863d7232e69bdfc76f6f3_1546949844.jpeg?fit=around%7C100%3A100&crop=100%3A100%3B%2A%2C%2A", "order": 0, "md5sum": "858beffe30c863d7232e69bdfc76f6f3", "id": 400906, "photo_id": 400906, "uuid": 1546949843655638, "type": "NORMAL"}}], "restaurants": [], "is_valid": 1, "share_url": "http://www.zoma.to/r/0", "show_share_url": 0, "title": "Vayu Vocal feat. Live Music", "description": "Soulful musicians performing live at Vayu Bar every night.", "display_time": "08:00 pm - 11:00 pm", "display_date": "08 January - 31 January", "is_end_time_set": 1, "disclaimer": "Restaurants are solely responsible for the service; availability and quality of the events including all or any cancellations/ modifications/ complaints.", "event_category": 0, "event_category_name": "", "book_link": "", "types": [{"name": "Solo Performance", "color": "#6454B8"}], "share_data": {"should_show": 0}}}], "opentable_support": 0, "is_zomato_book_res": 0, "mezzo_provider": "OTHER", "is_book_form_web_view": 0, "book_form_web_view_url": "", "book_again_url": "", "thumb": "https://b.zmtcdn.com/data/pictures/3/18759923/5e550e93a8d4514d966f347b1e3fd062.jpeg?fit=around%7C200%3A200&crop=200%3A200%3B%2A%2C%2A", "user_rating": {"aggregate_rating": "4.2", "rating_text": "Very Good", "rating_color": "5BA829", "votes": "587"}, "photos_url": "https://www.zomato.com/ncr/duty-free-vayu-bar-sector-29-gurgaon/photos?utm_source=api_basic_user&utm_medium=api&utm_campaign=v2.1#tabtop", "menu_url": "https://www.zomato.com/ncr/duty-free-vayu-bar-sector-29-gurgaon/menu?utm_source=api_basic_user&utm_medium=api&utm_campaign=v2.1&openSwipeBox=menu&showMinimal=1#tabtop", "featured_image": "https://b.zmtcdn.com/data/pictures/3/18759923/5e550e93a8d4514d966f347b1e3fd062.jpeg?output-format=webp", "medio_provider": 1, "has_online_delivery": 0, "is_delivering_now": 0, "include_bogo_offers": true, "deeplink": "zomato://restaurant/18759923", "is_table_reservation_supported": 1, "has_table_booking": 0, "events_url": "https://www.zomato.com/ncr/duty-free-vayu-bar-sector-29-gurgaon/events#tabtop?utm_source=api_basic_user&utm_medium=api&utm_campaign=v2.1", "establishment_types": []}}, {"restaurant": {"R": {"res_id": 304299}, "apikey": "745c5f1b6907194a76b81269f31e9046", "id": "304299", "name": "The Flying Saucer Cafe", "url": "https://www.zomato.com/ncr/the-flying-saucer-cafe-nehru-place-new-delhi?utm_source=api_basic_user&utm_medium=api&utm_campaign=v2.1", "location": {"address": "Ground Floor, Epicuria Food Mall, Nehru Place Metro Station, Nehru Place, New Delhi", "locality": "Epicuria Food Mall, Nehru Place", "city": "New Delhi", "city_id": 1, "latitude": "28.5508567238", "longitude": "77.2525491938", "zipcode": "", "country_id": 1, "locality_verbose": "Epicuria Food Mall, Nehru Place, New Delhi"}, "switch_to_order_menu": 0, "cuisines": "Continental, Bar Food", "average_cost_for_two": 1600, "price_range": 3, "currency": "Rs.", "offers": [], "opentable_support": 0, "is_zomato_book_res": 0, "mezzo_provider": "OTHER", "is_book_form_web_view": 0, "book_form_web_view_url": "", "book_again_url": "", "thumb": "https://b.zmtcdn.com/data/pictures/chains/9/304299/57feec7889d494319fc4faf25af3e393.jpg?fit=around%7C200%3A200&crop=200%3A200%3B%2A%2C%2A", "user_rating": {"aggregate_rating": "4.4", "rating_text": "Very Good", "rating_color": "5BA829", "votes": "7169"}, "photos_url": "https://www.zomato.com/ncr/the-flying-saucer-cafe-nehru-place-new-delhi/photos?utm_source=api_basic_user&utm_medium=api&utm_campaign=v2.1#tabtop", "menu_url": "https://www.zomato.com/ncr/the-flying-saucer-cafe-nehru-place-new-delhi/menu?utm_source=api_basic_user&utm_medium=api&utm_campaign=v2.1&openSwipeBox=menu&showMinimal=1#tabtop", "featured_image": "https://b.zmtcdn.com/data/pictures/chains/9/304299/57feec7889d494319fc4faf25af3e393.jpg", "medio_provider": 1, "has_online_delivery": 1, "is_delivering_now": 0, "include_bogo_offers": true, "deeplink": "zomato://restaurant/304299", "is_table_reservation_supported": 1, "has_table_booking": 0, "events_url": "https://www.zomato.com/ncr/the-flying-saucer-cafe-nehru-place-new-delhi/events#tabtop?utm_source=api_basic_user&utm_medium=api&utm_campaign=v2.1", "establishment_types": []}}, {"restaurant": {"R": {"res_id": 301605}, "apikey": "745c5f1b6907194a76b81269f31e9046", "id": "301605", "name": "Warehouse Cafe", "url": "https://www.zomato.com/ncr/warehouse-cafe-connaught-place-new-delhi?utm_source=api_basic_user&utm_medium=api&utm_campaign=v2.1", "location": {"address": "D 19/ 20, D Block, Inner Circle, Near Rajiv Chowk Metro Station Gate 3, Connaught Place, New Delhi", "locality": "Connaught Place", "city": "New Delhi", "city_id": 1, "latitude": "28.6337385011", "longitude": "77.2209410369", "zipcode": "110001", "country_id": 1, "locality_verbose": "Connaught Place, New Delhi"}, "switch_to_order_menu": 0, "cuisines": "American, Continental, Italian, North Indian, Asian, Salad, Juices, Momos", "average_cost_for_two": 1500, "price_range": 3, "currency": "Rs.", "offers": [], "opentable_support": 0, "is_zomato_book_res": 0, "mezzo_provider": "OTHER", "is_book_form_web_view": 0, "book_form_web_view_url": "", "book_again_url": "", "thumb": "https://b.zmtcdn.com/data/pictures/5/301605/ad6055849b2598139fbccae3efbc82e2.png?fit=around%7C200%3A200&crop=200%3A200%3B%2A%2C%2A", "user_rating": {"aggregate_rating": "4.4", "rating_text": "Very Good", "rating_color": "5BA829", "votes": "9202"}, "photos_url": "https://www.zomato.com/ncr/warehouse-cafe-connaught-place-new-delhi/photos?utm_source=api_basic_user&utm_medium=api&utm_campaign=v2.1#tabtop", "menu_url": "https://www.zomato.com/ncr/warehouse-cafe-connaught-place-new-delhi/menu?utm_source=api_basic_user&utm_medium=api&utm_campaign=v2.1&openSwipeBox=menu&showMinimal=1#tabtop", "featured_image": "https://b.zmtcdn.com/data/pictures/5/301605/ad6055849b2598139fbccae3efbc82e2.png", "medio_provider": 1, "has_online_delivery": 0, "is_delivering_now": 0, "include_bogo_offers": true, "deeplink": "zomato://restaurant/301605", "is_table_reservation_supported": 1, "has_table_booking": 0, "events_url": "https://www.zomato.com/ncr/warehouse-cafe-connaught-place-new-delhi/events#tabtop?utm_source=api_basic_user&utm_medium=api&utm_campaign=v2.1", "establishment_types": []}}, {"restaurant": {"R": {"res_id": 18400720}, "apikey": "745c5f1b6907194a76b81269f31e9046", "id": "18400720", "name": "Mama's Buoi", "url": "https://www.zomato.com/ncr/mamas-buoi-delhi-university-gtb-nagar?utm_source=api_basic_user&utm_medium=api&utm_campaign=v2.1", "location": {"address": "3rd Floor, 2624, Hudson Lane, Delhi University-GTB Nagar, New Delhi", "locality": "Delhi University-GTB Nagar", "city": "New Delhi", "city_id": 1, "latitude": "28.6931222861", "longitude": "77.2053506970", "zipcode": "", "country_id": 1, "locality_verbose": "Delhi University-GTB Nagar, New Delhi"}, "switch_to_order_menu": 0, "cuisines": "North Indian, Continental, Italian, Momos", "average_cost_for_two": 1000, "price_range": 3, "currency": "Rs.", "offers": [], "opentable_support": 0, "is_zomato_book_res": 0, "mezzo_provider": "OTHER", "is_book_form_web_view": 0, "book_form_web_view_url": "", "book_again_url": "", "thumb": "https://b.zmtcdn.com/data/pictures/chains/0/18400720/87da022c990240245f9d28f8fc21d786.png?fit=around%7C200%3A200&crop=200%3A200%3B%2A%2C%2A", "user_rating": {"aggregate_rating": "4.6", "rating_text": "Excellent", "rating_color": "3F7E00", "votes": "2486"}, "photos_url": "https://www.zomato.com/ncr/mamas-buoi-delhi-university-gtb-nagar/photos?utm_source=api_basic_user&utm_medium=api&utm_campaign=v2.1#tabtop", "menu_url": "https://www.zomato.com/ncr/mamas-buoi-delhi-university-gtb-nagar/menu?utm_source=api_basic_user&utm_medium=api&utm_campaign=v2.1&openSwipeBox=menu&showMinimal=1#tabtop", "featured_image": "https://b.zmtcdn.com/data/pictures/chains/0/18400720/87da022c990240245f9d28f8fc21d786.png?output-format=webp", "medio_provider": 1, "has_online_delivery": 0, "is_delivering_now": 0, "include_bogo_offers": true, "deeplink": "zomato://restaurant/18400720", "is_table_reservation_supported": 1, "has_table_booking": 0, "events_url": "https://www.zomato.com/ncr/mamas-buoi-delhi-university-gtb-nagar/events#tabtop?utm_source=api_basic_user&utm_medium=api&utm_campaign=v2.1", "establishment_types": []}}, {"restaurant": {"R": {"res_id": 18472653}, "apikey": "745c5f1b6907194a76b81269f31e9046", "id": "18472653", "name": "Marine Drivve - Club & Courtyard", "url": "https://www.zomato.com/ncr/marine-drivve-club-courtyard-rajouri-garden-new-delhi?utm_source=api_basic_user&utm_medium=api&utm_campaign=v2.1", "location": {"address": "A-2, Vishal Enclave, Opposite Metro Pillar 412, Rajouri Garden, New Delhi", "locality": "Rajouri Garden", "city": "New Delhi", "city_id": 1, "latitude": "28.6477955297", "longitude": "77.1187877655", "zipcode": "", "country_id": 1, "locality_verbose": "Rajouri Garden, New Delhi"}, "switch_to_order_menu": 0, "cuisines": "North Indian, Chinese, Italian, Momos", "average_cost_for_two": 1300, "price_range": 3, "currency": "Rs.", "offers": [], "zomato_events": [{"event": {"event_id": 297845, "friendly_start_date": "12 January", "friendly_end_date": "31 January", "friendly_timing_str": "Saturday, 12th January - Thursday, 31st January", "start_date": "2019-01-12", "end_date": "2019-01-31", "end_time": "23:55:00", "start_time": "12:00:00", "is_active": 1, "date_added": "2019-01-10 13:33:55", "photos": [{"photo": {"url": "https://b.zmtcdn.com/data/zomato_events/photos/38f/ead0f5f92ec1a85d1a35f9352ccc238f_1547107435.jpeg", "thumb_url": "https://b.zmtcdn.com/data/zomato_events/photos/38f/ead0f5f92ec1a85d1a35f9352ccc238f_1547107435.jpeg?fit=around%7C100%3A100&crop=100%3A100%3B%2A%2C%2A", "order": 0, "md5sum": "ead0f5f92ec1a85d1a35f9352ccc238f", "id": 401861, "photo_id": 401861, "uuid": 1547107423258220, "type": "NORMAL"}}], "restaurants": [], "is_valid": 1, "share_url": "http://www.zoma.to/r/0", "show_share_url": 0, "title": "BBQ FESTIVAL SEASON 2 ", "description": "Get Unlimited Food & Drinks starting @799/-. \n\nBook Table Now. \n\nT&C ", "display_time": "12:00 pm - 11:55 pm", "display_date": "12 January - 31 January", "is_end_time_set": 1, "disclaimer": "Restaurants are solely responsible for the service; availability and quality of the events including all or any cancellations/ modifications/ complaints.", "event_category": 0, "event_category_name": "", "book_link": "", "types": [], "share_data": {"should_show": 0}}}], "opentable_support": 0, "is_zomato_book_res": 1, "mezzo_provider": "ZOMATO_BOOK", "is_book_form_web_view": 0, "book_form_web_view_url": "", "thumb": "https://b.zmtcdn.com/data/pictures/3/18472653/d1a85d999e3ce817044e1714427b7bac.png?fit=around%7C200%3A200&crop=200%3A200%3B%2A%2C%2A", "user_rating": {"aggregate_rating": "4.7", "rating_text": "Excellent", "rating_color": "3F7E00", "votes": "2091"}, "photos_url": "https://www.zomato.com/ncr/marine-drivve-club-courtyard-rajouri-garden-new-delhi/photos?utm_source=api_basic_user&utm_medium=api&utm_campaign=v2.1#tabtop", "menu_url": "https://www.zomato.com/ncr/marine-drivve-club-courtyard-rajouri-garden-new-delhi/menu?utm_source=api_basic_user&utm_medium=api&utm_campaign=v2.1&openSwipeBox=menu&showMinimal=1#tabtop", "featured_image": "https://b.zmtcdn.com/data/pictures/3/18472653/d1a85d999e3ce817044e1714427b7bac.png?output-format=webp", "medio_provider": "", "has_online_delivery": 0, "is_delivering_now": 0, "include_bogo_offers": true, "deeplink": "zomato://restaurant/18472653", "is_table_reservation_supported": 1, "has_table_booking": 1, "book_url": "https://www.zomato.com/ncr/marine-drivve-club-courtyard-rajouri-garden-new-delhi/book?utm_source=api_basic_user&utm_medium=api&utm_campaign=v2.1", "events_url": "https://www.zomato.com/ncr/marine-drivve-club-courtyard-rajouri-garden-new-delhi/events#tabtop?utm_source=api_basic_user&utm_medium=api&utm_campaign=v2.1", "establishment_types": []}}, {"restaurant": {"R": {"res_id": 18856789}, "apikey": "745c5f1b6907194a76b81269f31e9046", "id": "18856789", "name": "AIR- An Ivory Region", "url": "https://www.zomato.com/ncr/air-an-ivory-region-punjabi-bagh-new-delhi?utm_source=api_basic_user&utm_medium=api&utm_campaign=v2.1", "location": {"address": "1/83, Third Floor, Club Road, West Punjabi Bagh, Punjabi Bagh, New Delhi", "locality": "Punjabi Bagh", "city": "New Delhi", "city_id": 1, "latitude": "28.5478090000", "longitude": "76.9869859000", "zipcode": "", "country_id": 1, "locality_verbose": "Punjabi Bagh, New Delhi"}, "switch_to_order_menu": 0, "cuisines": "North Indian, Chinese, Continental, Asian", "average_cost_for_two": 1000, "price_range": 3, "currency": "Rs.", "offers": [], "zomato_events": [{"event": {"event_id": 298513, "friendly_start_date": "13 January", "friendly_end_date": "14 January", "friendly_timing_str": "Sunday, 13th January - Monday, 14th January", "start_date": "2019-01-13", "end_date": "2019-01-14", "end_time": "00:00:00", "start_time": "21:00:00", "is_active": 1, "date_added": "2019-01-11 17:30:53", "photos": [{"photo": {"url": "https://b.zmtcdn.com/data/zomato_events/photos/87e/8e92f3b7bc015f054c5bb1c3a37fa87e_1547208115.jpeg", "thumb_url": "https://b.zmtcdn.com/data/zomato_events/photos/87e/8e92f3b7bc015f054c5bb1c3a37fa87e_1547208115.jpeg?fit=around%7C100%3A100&crop=100%3A100%3B%2A%2C%2A", "order": 0, "md5sum": "8e92f3b7bc015f054c5bb1c3a37fa87e", "id": 402733, "photo_id": 402733, "uuid": 1547208112853539, "type": "NORMAL"}}], "restaurants": [], "is_valid": 1, "share_url": "http://www.zoma.to/r/0", "show_share_url": 0, "title": "Sunday Spree Ft. Dj Ansh & Shivam", "description": "Hot and Happening Sunday spree night is here! All party animals do not miss Sunday Spree at AIR - An Ivory Region \n\nFor Reservations: 9999122038, 9999122074", "display_time": "09:00 pm - 12:00 am", "display_date": "13 January - 14 January", "is_end_time_set": 1, "disclaimer": "Restaurants are solely responsible for the service; availability and quality of the events including all or any cancellations/ modifications/ complaints.", "event_category": 0, "event_category_name": "", "book_link": "", "types": [{"name": "Live DJ", "color": "#6454B8"}], "share_data": {"should_show": 0}}}], "opentable_support": 0, "is_zomato_book_res": 1, "mezzo_provider": "ZOMATO_BOOK", "is_book_form_web_view": 0, "book_form_web_view_url": "", "thumb": "https://b.zmtcdn.com/data/pictures/9/18856789/df647751670debb136669d2568b94e49.jpeg?fit=around%7C200%3A200&crop=200%3A200%3B%2A%2C%2A", "user_rating": {"aggregate_rating": "3.8", "rating_text": "Good", "rating_color": "9ACD32", "votes": "553"}, "photos_url": "https://www.zomato.com/ncr/air-an-ivory-region-punjabi-bagh-new-delhi/photos?utm_source=api_basic_user&utm_medium=api&utm_campaign=v2.1#tabtop", "menu_url": "https://www.zomato.com/ncr/air-an-ivory-region-punjabi-bagh-new-delhi/menu?utm_source=api_basic_user&utm_medium=api&utm_campaign=v2.1&openSwipeBox=menu&showMinimal=1#tabtop", "featured_image": "https://b.zmtcdn.com/data/pictures/9/18856789/df647751670debb136669d2568b94e49.jpeg", "medio_provider": "", "has_online_delivery": 0, "is_delivering_now": 0, "include_bogo_offers": true, "deeplink": "zomato://restaurant/18856789", "is_table_reservation_supported": 1, "has_table_booking": 1, "book_url": "https://www.zomato.com/ncr/air-an-ivory-region-punjabi-bagh-new-delhi/book?utm_source=api_basic_user&utm_medium=api&utm_campaign=v2.1", "events_url": "https://www.zomato.com/ncr/air-an-ivory-region-punjabi-bagh-new-delhi/events#tabtop?utm_source=api_basic_user&utm_medium=api&utm_campaign=v2.1", "establishment_types": []}}, {"restaurant": {"R": {"res_id": 18268712}, "apikey": "745c5f1b6907194a76b81269f31e9046", "id": "18268712", "name": "Chili's Grill & Bar", "url": "https://www.zomato.com/ncr/chilis-grill-bar-sector-18-noida?utm_source=api_basic_user&utm_medium=api&utm_campaign=v2.1", "location": {"address": "3rd Floor, DLF Mall Of India, Sector 18, Noida", "locality": "DLF Mall of India, Sector 18,  Noida", "city": "Noida", "city_id": 1, "latitude": "28.5673406049", "longitude": "77.3210340366", "zipcode": "", "country_id": 1, "locality_verbose": "DLF Mall of India, Sector 18,  Noida, Noida"}, "switch_to_order_menu": 0, "cuisines": "Mexican, American, Italian", "average_cost_for_two": 1500, "price_range": 3, "currency": "Rs.", "offers": [], "zomato_events": [{"event": {"event_id": 269994, "friendly_start_date": "01 November, 2018", "friendly_end_date": "31 March", "friendly_timing_str": "Thursday, 1st November - Sunday, 31st March", "start_date": "2018-11-01", "end_date": "2019-03-31", "end_time": "20:00:00", "start_time": "16:00:00", "is_active": 1, "date_added": "2018-11-01 14:13:06", "photos": [{"photo": {"url": "https://b.zmtcdn.com/data/zomato_events/photos/b78/10bec8698a95407c4909b69f77d2ab78_1541061786.jpg", "thumb_url": "https://b.zmtcdn.com/data/zomato_events/photos/b78/10bec8698a95407c4909b69f77d2ab78_1541061786.jpg?fit=around%7C100%3A100&crop=100%3A100%3B%2A%2C%2A", "order": 0, "md5sum": "10bec8698a95407c4909b69f77d2ab78", "id": 367664, "photo_id": 367664, "uuid": 1541061737509839, "type": "NORMAL"}}], "restaurants": [], "is_valid": 1, "share_url": "http://www.zoma.to/r/0", "show_share_url": 0, "title": "Happy Hour", "description": "Enjoy Happy Hour on Drinks from 4 P.M. to 8 P.M. Monday to Friday", "display_time": "04:00 pm - 08:00 pm", "display_date": "01 November - 31 March", "is_end_time_set": 1, "disclaimer": "Restaurants are solely responsible for the service; availability and quality of the events including all or any cancellations/ modifications/ complaints.", "event_category": 0, "event_category_name": "", "book_link": "", "types": [{"name": "Happy Hours", "color": "#E23744"}], "share_data": {"should_show": 0}}}], "opentable_support": 0, "is_zomato_book_res": 0, "mezzo_provider": "OTHER", "is_book_form_web_view": 0, "book_form_web_view_url": "", "book_again_url": "", "thumb": "https://b.zmtcdn.com/data/res_imagery/4751_CHAIN_a5bff706786fbed7313bd8b8b6271ea8.jpg?fit=around%7C200%3A200&crop=200%3A200%3B%2A%2C%2A", "user_rating": {"aggregate_rating": "4.5", "rating_text": "Excellent", "rating_color": "3F7E00", "votes": "2946"}, "photos_url": "https://www.zomato.com/ncr/chilis-grill-bar-sector-18-noida/photos?utm_source=api_basic_user&utm_medium=api&utm_campaign=v2.1#tabtop", "menu_url": "https://www.zomato.com/ncr/chilis-grill-bar-sector-18-noida/menu?utm_source=api_basic_user&utm_medium=api&utm_campaign=v2.1&openSwipeBox=menu&showMinimal=1#tabtop", "featured_image": "https://b.zmtcdn.com/data/res_imagery/4751_CHAIN_a5bff706786fbed7313bd8b8b6271ea8.jpg?output-format=webp", "medio_provider": 1, "has_online_delivery": 1, "is_delivering_now": 0, "include_bogo_offers": true, "deeplink": "zomato://restaurant/18268712", "is_table_reservation_supported": 1, "has_table_booking": 0, "events_url": "https://www.zomato.com/ncr/chilis-grill-bar-sector-18-noida/events#tabtop?utm_source=api_basic_user&utm_medium=api&utm_campaign=v2.1", "establishment_types": []}}, {"restaurant": {"R": {"res_id": 18418247}, "apikey": "745c5f1b6907194a76b81269f31e9046", "id": "18418247", "name": "Feel Alive", "url": "https://www.zomato.com/ncr/feel-alive-sector-29-gurgaon?utm_source=api_basic_user&utm_medium=api&utm_campaign=v2.1", "location": {"address": "SCO 53, 2nd Floor, Main Market, Sector 29, Gurgaon", "locality": "Sector 29", "city": "Gurgaon", "city_id": 1, "latitude": "28.4679370709", "longitude": "77.0641377568", "zipcode": "", "country_id": 1, "locality_verbose": "Sector 29, Gurgaon"}, "switch_to_order_menu": 0, "cuisines": "North Indian, Fast Food", "average_cost_for_two": 1200, "price_range": 3, "currency": "Rs.", "offers": [], "zomato_events": [{"event": {"event_id": 235550, "friendly_start_date": "13 January", "friendly_end_date": "13 January", "friendly_timing_str": "Sunday, 13th January", "start_date": "2019-01-13", "end_date": "2019-01-13", "end_time": "22:00:00", "start_time": "19:00:00", "is_active": 1, "date_added": "2018-07-13 15:03:28", "photos": [{"photo": {"url": "https://b.zmtcdn.com/data/zomato_events/photos/ae4/0d70ae330eb6e9a90aa8983a45eebae4_1531474408.png", "thumb_url": "https://b.zmtcdn.com/data/zomato_events/photos/ae4/0d70ae330eb6e9a90aa8983a45eebae4_1531474408.png?fit=around%7C100%3A100&crop=100%3A100%3B%2A%2C%2A", "order": 0, "md5sum": "0d70ae330eb6e9a90aa8983a45eebae4", "id": 326310, "photo_id": 326310, "uuid": 1531474400905990, "type": "NORMAL"}}], "restaurants": [], "is_valid": 1, "share_url": "http://www.zoma.to/r/0", "show_share_url": 0, "title": "LADIES NIGHT (DRINKS ON THE HOUSE FOR LADIES)", "description": "That could be more fun than all girls night with drinks on the house? Yeah, sounds soo good!! We've got you covered! So, mark your day and choose your outfit, get ready to slay at our Ladies Night!\n\n2 Complimentary Drinks Each", "display_time": "07:00 pm - 10:00 pm", "display_date": "13 January", "is_end_time_set": 1, "disclaimer": "Restaurants are solely responsible for the service; availability and quality of the events including all or any cancellations/ modifications/ complaints.", "event_category": 0, "event_category_name": "", "book_link": "", "types": [{"name": "Ladies Night", "color": "#0AAC9B"}], "share_data": {"should_show": 0}}}], "opentable_support": 0, "is_zomato_book_res": 0, "mezzo_provider": "OTHER", "is_book_form_web_view": 0, "book_form_web_view_url": "", "book_again_url": "", "thumb": "https://b.zmtcdn.com/data/res_imagery/18418247_RESTAURANT_21f3654cca54cbf08128a1421b245612.jpg?fit=around%7C200%3A200&crop=200%3A200%3B%2A%2C%2A", "user_rating": {"aggregate_rating": "4.7", "rating_text": "Excellent", "rating_color": "3F7E00", "votes": "1710"}, "photos_url": "https://www.zomato.com/ncr/feel-alive-sector-29-gurgaon/photos?utm_source=api_basic_user&utm_medium=api&utm_campaign=v2.1#tabtop", "menu_url": "https://www.zomato.com/ncr/feel-alive-sector-29-gurgaon/menu?utm_source=api_basic_user&utm_medium=api&utm_campaign=v2.1&openSwipeBox=menu&showMinimal=1#tabtop", "featured_image": "https://b.zmtcdn.com/data/res_imagery/18418247_RESTAURANT_21f3654cca54cbf08128a1421b245612.jpg", "medio_provider": 1, "has_online_delivery": 0, "is_delivering_now": 0, "include_bogo_offers": true, "deeplink": "zomato://restaurant/18418247", "is_table_reservation_supported": 1, "has_table_booking": 0, "events_url": "https://www.zomato.com/ncr/feel-alive-sector-29-gurgaon/events#tabtop?utm_source=api_basic_user&utm_medium=api&utm_campaign=v2.1", "establishment_types": []}}, {"restaurant": {"R": {"res_id": 301232}, "apikey": "745c5f1b6907194a76b81269f31e9046", "id": "301232", "name": "Chili's Grill & Bar", "url": "https://www.zomato.com/ncr/chilis-grill-bar-saket-new-delhi?utm_source=api_basic_user&utm_medium=api&utm_campaign=v2.1", "location": {"address": "161-A, Ground Floor, DLF Place Mall, Saket, New Delhi", "locality": "DLF Place Mall, Saket", "city": "New Delhi", "city_id": 1, "latitude": "28.5284039752", "longitude": "77.2160654515", "zipcode": "", "country_id": 1, "locality_verbose": "DLF Place Mall, Saket, New Delhi"}, "switch_to_order_menu": 0, "cuisines": "Mexican, American, Italian, Salad", "average_cost_for_two": 1500, "price_range": 3, "currency": "Rs.", "offers": [], "opentable_support": 0, "is_zomato_book_res": 0, "mezzo_provider": "OTHER", "is_book_form_web_view": 0, "book_form_web_view_url": "", "book_again_url": "", "thumb": "https://b.zmtcdn.com/data/res_imagery/4751_CHAIN_a5bff706786fbed7313bd8b8b6271ea8.jpg?fit=around%7C200%3A200&crop=200%3A200%3B%2A%2C%2A", "user_rating": {"aggregate_rating": "4.5", "rating_text": "Excellent", "rating_color": "3F7E00", "votes": "3949"}, "photos_url": "https://www.zomato.com/ncr/chilis-grill-bar-saket-new-delhi/photos?utm_source=api_basic_user&utm_medium=api&utm_campaign=v2.1#tabtop", "menu_url": "https://www.zomato.com/ncr/chilis-grill-bar-saket-new-delhi/menu?utm_source=api_basic_user&utm_medium=api&utm_campaign=v2.1&openSwipeBox=menu&showMinimal=1#tabtop", "featured_image": "https://b.zmtcdn.com/data/res_imagery/4751_CHAIN_a5bff706786fbed7313bd8b8b6271ea8.jpg", "medio_provider": 1, "has_online_delivery": 1, "is_delivering_now": 0, "include_bogo_offers": true, "deeplink": "zomato://restaurant/301232", "is_table_reservation_supported": 1, "has_table_booking": 0, "events_url": "https://www.zomato.com/ncr/chilis-grill-bar-saket-new-delhi/events#tabtop?utm_source=api_basic_user&utm_medium=api&utm_campaign=v2.1", "establishment_types": []}}]}